.gitignore
CHANGES.txt
README.rst
bootstrap.py
buildout.cfg
setup.py
collective/__init__.py
collective.js.pikachoose.egg-info/PKG-INFO
collective.js.pikachoose.egg-info/SOURCES.txt
collective.js.pikachoose.egg-info/dependency_links.txt
collective.js.pikachoose.egg-info/entry_points.txt
collective.js.pikachoose.egg-info/namespace_packages.txt
collective.js.pikachoose.egg-info/not-zip-safe
collective.js.pikachoose.egg-info/requires.txt
collective.js.pikachoose.egg-info/top_level.txt
collective/js/__init__.py
collective/js/pikachoose/__init__.py
collective/js/pikachoose/configure.zcml
collective/js/pikachoose/upgrades.py
collective/js/pikachoose/profiles/default/jsregistry.xml
collective/js/pikachoose/profiles/default/metadata.xml
collective/js/pikachoose/resources/js/jquery.pikachoose.full.js
collective/js/pikachoose/resources/js/jquery.pikachoose.js
collective/js/pikachoose/resources/styles/75-black.png
collective/js/pikachoose/resources/styles/base.css
collective/js/pikachoose/resources/styles/basic.png
collective/js/pikachoose/resources/styles/black.png
collective/js/pikachoose/resources/styles/bottom.css
collective/js/pikachoose/resources/styles/css3.css
collective/js/pikachoose/resources/styles/fastf.png
collective/js/pikachoose/resources/styles/left-without.css
collective/js/pikachoose/resources/styles/left.css
collective/js/pikachoose/resources/styles/loading.gif
collective/js/pikachoose/resources/styles/next-horizontal.png
collective/js/pikachoose/resources/styles/next-vertical.png
collective/js/pikachoose/resources/styles/next.png
collective/js/pikachoose/resources/styles/pause.png
collective/js/pikachoose/resources/styles/play.png
collective/js/pikachoose/resources/styles/prev-horizontal.png
collective/js/pikachoose/resources/styles/prev-vertical.png
collective/js/pikachoose/resources/styles/prev.png
collective/js/pikachoose/resources/styles/rewind.png
collective/js/pikachoose/resources/styles/right-without.css
collective/js/pikachoose/resources/styles/right.css
collective/js/pikachoose/resources/styles/simple.css
collective/js/pikachoose/resources/styles/tooltip.css
collective/js/pikachoose/resources/styles/transitions.css
collective/js/pikachoose/tests/__init__.py
collective/js/pikachoose/tests/base.py
collective/js/pikachoose/tests/test_setup.py